{
  "name": "免费在线 XMind 查看器（本地解析/大纲导出）- 纯粹工具站",
  "shortName": "XMind 查看器",
  "description": "在线打开并预览 .xmind（支持 XMind 2020/8），本地解析生成大纲与 Canvas 预览，可复制/下载 Markdown，不上传文件。",
  "seoDescription": "免费在线 XMind 查看器：直接在浏览器打开 .xmind（支持 content.json 与 content.xml），本地解析不上传文件，快速预览思维导图；支持 Canvas 大图查看（拖拽/缩放/自适应）以及导出/复制 Markdown 大纲，适用于学习笔记、项目规划、会议记录与知识管理。",
  "lang": "zh-CN",
  "themeColor": "#0f172a",
  "backgroundColor": "#0f172a",
  "icon": "/icon.svg",
  "category": "文档工具",
  "keywords": [
    "XMind查看器",
    "XMind在线查看",
    "在线打开xmind",
    "xmind文件预览",
    "xmind阅读器",
    "xmind打开器",
    "xmind转大纲",
    "xmind导出markdown",
    "xmind转markdown",
    "xmind转文本",
    "思维导图查看",
    "思维导图预览",
    "思维导图转大纲",
    "XMind 8",
    "XMind 2020",
    "XMind Zen",
    "content.json",
    "content.xml",
    "本地解析",
    "隐私不上传",
    "浏览器查看xmind"
  ]
}
